{"trial_id": "0086", "hyperparameters": {"space": [{"class_name": "Int", "config": {"name": "units1", "default": null, "conditions": [], "min_value": 32, "max_value": 512, "step": 32, "sampling": null}}, {"class_name": "Int", "config": {"name": "units2", "default": null, "conditions": [], "min_value": 32, "max_value": 512, "step": 32, "sampling": null}}, {"class_name": "Int", "config": {"name": "units3", "default": null, "conditions": [], "min_value": 32, "max_value": 512, "step": 32, "sampling": null}}, {"class_name": "Choice", "config": {"name": "learning_rate", "default": 0.01, "conditions": [], "values": [0.01, 0.001, 0.0001], "ordered": true}}], "values": {"units1": 192, "units2": 224, "units3": 224, "learning_rate": 0.01, "tuner/epochs": 60, "tuner/initial_epoch": 0, "tuner/bracket": 0, "tuner/round": 0}}, "metrics": {"metrics": {"loss": {"direction": "min", "observations": [{"value": [3.381998300552368], "step": 58}]}, "val_loss": {"direction": "min", "observations": [{"value": [2.2766575813293457], "step": 58}]}}}, "score": 2.2766575813293457, "best_step": 58, "status": "COMPLETED"}